experder/__init__.py
experder-0.1.0.dist-info/LICENSE
experder-0.1.0.dist-info/METADATA
experder-0.1.0.dist-info/WHEEL
experder-0.1.0.dist-info/top_level.txt
experder-0.1.0.dist-info/RECORD
