Metadata-Version: 2.1
Name: experder
Version: 0.1.0
Summary: Python library for basic encryption like caesar encrypt and 10-key encryption
Home-page: https://github.com/feimaomiao/experder
Author: Matthew Lam
Author-email: lcpmatthew@gmail.com
License: UNKNOWN
Keywords: caesar encryption
Platform: UNKNOWN
Classifier: Programming Language :: Python :: 3
Classifier: Programming Language :: Python :: 3.6
Classifier: Programming Language :: Python :: 3.7
Classifier: Programming Language :: Python :: 3.8
Classifier: Natural Language :: English
Classifier: License :: OSI Approved :: MIT License
Classifier: Intended Audience :: Developers
Classifier: Operating System :: OS Independent
Classifier: Topic :: Software Development :: Libraries :: Python Modules
Requires-Python: >=3.6
